genluhn/__init__.py
genluhn/py.typed
genluhn-0.3.1.dist-info/LICENSE.txt
genluhn-0.3.1.dist-info/METADATA
genluhn-0.3.1.dist-info/WHEEL
genluhn-0.3.1.dist-info/top_level.txt
genluhn-0.3.1.dist-info/RECORD
