Metadata-Version: 2.1
Name: genluhn
Version: 0.3.1
Summary: Generalized Luhn algorithm to any numeric base
Home-page: https://github.com/inab/genluhn
Author: José M. Fernández <https://orcid.org/0000-0002-4806-5140>
Author-email: jose.m.fernandez@bsc.es
License: LGPL-2.1
Project-URL: Bug Tracker, https://github.com/inab/genluhn/issues
Classifier: Programming Language :: Python :: 3
Classifier: Development Status :: 3 - Alpha
Classifier: License :: OSI Approved :: GNU Lesser General Public License v2 or later (LGPLv2+)
Classifier: Operating System :: OS Independent
Requires-Python: >=3.6
License-File: LICENSE.txt
